corvic_engine-0.2.50.dist-info/METADATA
corvic_engine-0.2.50.dist-info/WHEEL
corvic_engine-0.2.50.dist-info/licenses/LICENSE
corvic/context/py.typed
corvic/context/__init__.py
corvic/embed/node2vec.py
corvic/embed/py.typed
corvic/embed/__init__.py
corvic/embedding_metric/embeddings.py
corvic/embedding_metric/py.typed
corvic/embedding_metric/__init__.py
corvic/engine/py.typed
corvic/engine/_native.pyi
corvic/engine/__init__.py
corvic/execute/errors.py
corvic/execute/sandbox.py
corvic/execute/__init__.py
corvic/lazy_import/py.typed
corvic/lazy_import/__init__.py
corvic/model/py.typed
corvic/model/_agent.py
corvic/model/_defaults.py
corvic/model/_errors.py
corvic/model/_feature_type.py
corvic/model/_feature_view.py
corvic/model/_proto_orm_convert.py
corvic/model/_resource.py
corvic/model/_source.py
corvic/model/_space.py
corvic/model/_wrapped_proto.py
corvic/model/__init__.py
corvic/op_graph/aggregation.py
corvic/op_graph/encoders.py
corvic/op_graph/errors.py
corvic/op_graph/feature_types.py
corvic/op_graph/ops.py
corvic/op_graph/py.typed
corvic/op_graph/row_filters/_jsonlogic.py
corvic/op_graph/row_filters/_row_filters.py
corvic/op_graph/row_filters/__init__.py
corvic/op_graph/sample_strategy.py
corvic/op_graph/_schema.py
corvic/op_graph/__init__.py
corvic/orm/base.py
corvic/orm/errors.py
corvic/orm/func/utc_func.py
corvic/orm/func/uuid_func.py
corvic/orm/func/__init__.py
corvic/orm/ids.py
corvic/orm/keys.py
corvic/orm/mixins.py
corvic/orm/py.typed
corvic/orm/_proto_columns.py
corvic/orm/__init__.py
corvic/pa_scalar/py.typed
corvic/pa_scalar/_const.py
corvic/pa_scalar/_from_value.py
corvic/pa_scalar/_temporal.py
corvic/pa_scalar/_to_value.py
corvic/pa_scalar/_types.py
corvic/pa_scalar/__init__.py
corvic/proto_wrapper/py.typed
corvic/proto_wrapper/_errors.py
corvic/proto_wrapper/_wrappers.py
corvic/proto_wrapper/__init__.py
corvic/result/py.typed
corvic/result/__init__.py
corvic/sql/parse_ops.py
corvic/sql/py.typed
corvic/sql/__init__.py
corvic/system/client.py
corvic/system/in_memory_executor.py
corvic/system/op_graph_executor.py
corvic/system/py.typed
corvic/system/staging.py
corvic_engine-0.2.50.dist-info/RECORD
